Lab3/sev_segment.v
`timescale 1ns / 1ps

// sevseg_mux.v
// Multiplexes four 4-bit digits to drive a four-digit seven-segment display.
// Also implements blinking for the selected digit when in adjust mode.
module sev_segment(
    input  wire clk,          // Fast clock for multiplexing (≈200 Hz)
    input  wire clk_blink,    // Blink clock (≈1 Hz)
    input  wire adjust,       // Adjust mode flag (ADJ)
    input  wire sel,          // Select: 0 = minutes, 1 = seconds (which part to blink)
    input  wire [15:0] digits, // 4 digits: [min_tens, min_ones, sec_tens, sec_ones]
    output reg [6:0] seg,     // 7-segment output (active low)
    output reg [3:0] an       // Anode signals (active low)
);

  // A 2-bit counter to cycle through the 4 digits.
  reg [1:0] digit_sel = 0;
  always @(posedge clk) begin
      digit_sel <= digit_sel + 1;
  end
  
  // Select the current 4-bit digit to display.
  reg [3:0] digit;
  always @(*) begin
      case (digit_sel)
          2'd0: digit = digits[15:12];  // Minutes tens
          2'd1: digit = digits[11:8];   // Minutes ones
          2'd2: digit = digits[7:4];    // Seconds tens
          2'd3: digit = digits[3:0];    // Seconds ones
          default: digit = 4'd0;
      endcase
  end
  
  // Determine whether to blank (turn off) the digit.
  // In adjust mode, the selected portion blinks:
  // - If sel is 0 (minutes adjustment), blank digits 0 and 1.
  // - If sel is 1 (seconds adjustment), blank digits 2 and 3.
  reg blink;
  always @(*) begin
      if (adjust) begin
          if ((sel && (digit_sel == 2 || digit_sel == 3)) ||
              (~sel && (digit_sel == 0 || digit_sel == 1)))
              blink = ~clk_blink;  // Use blink clock to toggle display
          else
              blink = 1'b1;
      end else begin
          blink = 1'b1;
      end
  end
  
  // Seven-segment decoder: Convert 4-bit digit to 7-seg pattern.
  // (Assuming a common anode display where 0 turns on a segment.)
  reg [6:0] seg_temp;
  always @(*) begin
      case (digit)
          4'd0: seg_temp = 7'b1000000;
          4'd1: seg_temp = 7'b1111001;
          4'd2: seg_temp = 7'b0100100;
          4'd3: seg_temp = 7'b0110000;
          4'd4: seg_temp = 7'b0011001;
          4'd5: seg_temp = 7'b0010010;
          4'd6: seg_temp = 7'b0000010;
          4'd7: seg_temp = 7'b1111000;
          4'd8: seg_temp = 7'b0000000;
          4'd9: seg_temp = 7'b0010000;
          default: seg_temp = 7'b1111111; // Blank
      endcase
  end
  
  // Drive the segments: if blink is low, blank the display.
  always @(*) begin
      if (blink)
          seg = seg_temp;
      else
          seg = 7'b1111111;
  end
  
  // Anode control: Only the selected digit is active at a time (active low).
  always @(*) begin
      case (digit_sel)
          2'd0: an = 4'b0111;
          2'd1: an = 4'b1011;
          2'd2: an = 4'b1101;
          2'd3: an = 4'b1110;
          default: an = 4'b1111;
      endcase
  end
  
endmodule

Lab3/mod_6_counter.v
// mod6_counter.v
// A modulo-6 counter (counts from 0 to 5). It is useful for the tens digit of seconds (and minutes).

module mod6_counter (
    input  wire clk,       // Clock input
    input  wire reset,     // Asynchronous reset (active high)
    input  wire en,        // Enable signal
    output reg [3:0] count, // 4-bit output (0 to 5)
    output reg carry       // Carry output, high for one cycle when wrapping
);

  always @(posedge clk or posedge reset) begin
    if (reset) begin
      count <= 4'd0;
      carry <= 1'b0;
    end else if (en) begin
      if (count == 4'd5) begin
        count <= 4'd0;
        carry <= 1'b1;
      end else begin
        count <= count + 1;
        carry <= 1'b0;
      end
    end else begin
      carry <= 1'b0;
    end
  end

endmodule

Lab3/decade_counter.v
// Decade Counter Module (Modulo-10 Counter)
// This counter increments on each rising edge of 'clk' when 'en' is high.
// When the count reaches 9, it wraps around to 0 and asserts 'carry' for one clock cycle.
// An asynchronous reset (active high) sets the counter to 0.

module decade_counter (
    input wire clk,       // Clock input
    input wire reset,     // Asynchronous reset (active high)
    input wire en,        // Enable signal: counter increments when high
    output reg [3:0] count, // 4-bit counter output (values 0 to 9)
    output reg carry      // Carry output, high for one cycle when count wraps
);

  // Always block sensitive to the rising edge of clk or reset
  always @(posedge clk or posedge reset) begin
    if (reset) begin
      // Asynchronous reset: clear the counter and carry
      count <= 4'd0;
      carry <= 1'b0;
    end else if (en) begin
      if (count == 4'd9) begin
        // If count reaches 9, wrap back to 0 and generate a carry
        count <= 4'd0;
        carry <= 1'b1;
      end else begin
        // Otherwise, increment the counter and clear carry
        count <= count + 1;
        carry <= 1'b0;
      end
    end else begin
      // When enable is low, hold the count and ensure carry is low
      carry <= 1'b0;
    end
  end

endmodule

Lab3/minutes_counter.v
// minutes_counter.v
// Implements the minutes counter for the stopwatch.
// It consists of two cascaded counters: a decade counter (for the ones digit)
// and a modulo-6 counter (for the tens digit). When the ones digit wraps (9 -> 0),
// it increments the tens digit. When minutes reach 59, they wrap to 00.

module minutes_counter(
    input  wire clk,         // Clock input (can be minute_enable pulse in normal mode or 2Hz in adjust mode)
    input  wire reset,       // Asynchronous reset (active high)
    input  wire pause,       // Pause signal: when high, the counter holds its value
    output wire [3:0] min_ones, // Minutes ones digit (0-9)
    output wire [3:0] min_tens  // Minutes tens digit (0-5)
);

  // Enable signal: counting occurs only when pause is low.
  wire en = ~pause;

  // Internal wire for carry-out from the ones digit.
  wire ones_carry;

  // Instantiate the ones digit counter (modulo-10)
  decade_counter ones_counter (
    .clk(clk),
    .reset(reset),
    .en(en),
    .count(min_ones),
    .carry(ones_carry)
  );

  // Instantiate the tens digit counter (modulo-6)
  // It increments only when ones_counter wraps from 9 to 0.
  mod6_counter tens_counter (
    .clk(clk),
    .reset(reset),
    .en(ones_carry),
    .count(min_tens),
    .carry()  // Unused carry output
  );

endmodule

Lab3/seconds_counter.v
// seconds_counter.v
// This module implements the seconds counter for the stopwatch.
// It uses a modulo-10 counter for the ones digit and a modulo-6 counter for the tens digit.
// The counter increments on each tick of its input clock (which might be 1 Hz in normal mode or 2 Hz in adjust mode).
// When the seconds reach 59 and then wrap to 00, the tens counter produces a carry (minute_enable)
// which can be used to increment the minutes counter.

module seconds_counter(
    input  wire clk,           // Input tick: either a 1 Hz (normal) or 2 Hz (adjust mode) clock.
    input  wire reset,         // Asynchronous reset (active high)
    input  wire pause,         // Pause input: when high, the counter is frozen.
    output wire [3:0] sec_ones, // Seconds ones digit (0-9)
    output wire [3:0] sec_tens, // Seconds tens digit (0-5)
    output wire minute_enable  // One-cycle pulse: high when seconds roll over from 59 to 00.
);

  // When paused, disable counting.
  wire en = ~pause;

  // Wire to catch the carry from the ones digit.
  wire ones_carry;

  // Instantiate the ones digit counter (modulo-10)
  decade_counter ones_counter (
    .clk   (clk),
    .reset (reset),
    .en    (en),
    .count (sec_ones),
    .carry (ones_carry)
  );

  // Instantiate the tens digit counter (modulo-6)
  // It increments only when the ones digit rolls over (ones_carry).
  mod6_counter tens_counter (
    .clk   (clk),
    .reset (reset),
    .en    (ones_carry),   // Only increment tens when ones digit wraps from 9 to 0.
    .count (sec_tens),
    .carry (minute_enable) // This carry becomes high when the tens counter wraps (i.e. 5 -> 0).
  );

endmodule

Lab3/clock_divider.v
// clock_divider.v
// This module divides the 100 MHz master clock into four different clocks:
// - clk_2Hz: for adjusting the stopwatch at 2 Hz (half period = 0.25 sec)
// - clk_1Hz: for normal counting (half period = 0.5 sec)
// - clk_fast: a fast clock for display multiplexing and debouncing (e.g., 200 Hz)
// - clk_blink: for blinking in adjust mode (e.g., 1 Hz blinking)

module clock_divider(
    input  wire clk_100MHz, // 100 MHz master clock
    input  wire reset,      // Synchronous or asynchronous reset
    output reg clk_2Hz,     // 2 Hz clock output
    output reg clk_1Hz,     // 1 Hz clock output
    output reg clk_fast,    // Fast clock (e.g., 200 Hz)
    output reg clk_blink    // Blink clock (e.g., 1 Hz)
);

    // =====================================================
    // Define division parameters (number of master clock cycles for half period)
    // =====================================================
    // For a 2 Hz clock:
    //   Full period = 0.5 sec, so half period = 0.25 sec.
    //   Number of cycles = 100e6 * 0.25 = 25,000,000.
    localparam DIV_2HZ   = 25000000;
    
    // For a 1 Hz clock:
    //   Full period = 1 sec, so half period = 0.5 sec.
    //   Number of cycles = 100e6 * 0.5 = 50,000,000.
    localparam DIV_1HZ   = 50000000;
    
    // For the fast clock:
    //   Example: choose 200 Hz (full period = 1/200 = 0.005 sec, half period = 0.0025 sec).
    //   Number of cycles = 100e6 * 0.0025 = 250,000.
    localparam DIV_FAST  = 250000;
    
    // For the blink clock:
    //   Example: choose 1.6 Hz blinking (half period = 0.3125 sec = 50,000,000 cycles).
    localparam DIV_BLINK = 3125000;

    // =====================================================
    // Declare counters for each divider. (26 bits are sufficient here.)
    // =====================================================
    reg [25:0] counter_2Hz;
    reg [25:0] counter_1Hz;
    reg [25:0] counter_fast;
    reg [25:0] counter_blink;

    // -----------------------------------------------------
    // Divider for 2 Hz clock
    // -----------------------------------------------------
    always @(posedge clk_100MHz or posedge reset) begin
      if (reset) begin
        counter_2Hz <= 26'd0;
        clk_2Hz <= 1'b0;
      end else begin
        if (counter_2Hz >= DIV_2HZ - 1) begin
          counter_2Hz <= 26'd0;
          clk_2Hz <= ~clk_2Hz; // Toggle the 2 Hz clock output.
        end else begin
          counter_2Hz <= counter_2Hz + 1;
        end
      end
    end
    // -----------------------------------------------------
    // Divider for 1 Hz clock
    // -----------------------------------------------------
    always @(posedge clk_100MHz or posedge reset) begin
      if (reset) begin
        counter_1Hz <= 26'd0;
        clk_1Hz <= 1'b0;
      end else begin
        if (counter_1Hz >= DIV_1HZ - 1) begin
          counter_1Hz <= 26'd0;
          clk_1Hz <= ~clk_1Hz;
        end else begin
          counter_1Hz <= counter_1Hz + 1;
        end
      end
    end

    // -----------------------------------------------------
    // Divider for the fast clock (for display multiplexing and debouncing)
    // -----------------------------------------------------
    always @(posedge clk_100MHz or posedge reset) begin
      if (reset) begin
        counter_fast <= 26'd0;
        clk_fast <= 1'b0;
      end else begin
        if (counter_fast >= DIV_FAST - 1) begin
          counter_fast <= 26'd0;
          clk_fast <= ~clk_fast;
        end else begin
          counter_fast <= counter_fast + 1;
        end
      end
    end

    // -----------------------------------------------------
    // Divider for the blink clock (for blinking the selected digit in adjust mode)
    // -----------------------------------------------------
    always @(posedge clk_100MHz or posedge reset) begin
      if (reset) begin
        counter_blink <= 26'd0;
        clk_blink <= 1'b0;
      end else begin
        if (counter_blink >= DIV_BLINK - 1) begin
          counter_blink <= 26'd0;
          clk_blink <= ~clk_blink;
        end else begin
          counter_blink <= counter_blink + 1;
        end
      end
    end

endmodule

Lab3/debounce.v
// debounce.v
// A simple debouncer using a shift register.
// The button is sampled at the clk rate (≈200 Hz in our design).
module debounce(
    input  wire clk,       // Sampling clock (≈200 Hz)
    input  wire btn_in,    // Raw button input
    output reg  btn_out    // Debounced output
);
    reg [15:0] shift_reg = 16'd0;
    
    always @(posedge clk) begin
        shift_reg <= {shift_reg[14:0], btn_in};
        // When all bits are 1, consider the button pressed.
        if(shift_reg == 16'hFFFF)
            btn_out <= 1;
        else if(shift_reg == 16'h0000)
            btn_out <= 0;
    end
endmodule

Lab3/stopwatch.v
`timescale 1ns/1ps

// stopwatch.v
// Top-level module that connects the clock divider, counters,
// debouncers, and seven-segment display driver to form the stopwatch.

module stopwatch(
    input  wire clk_100MHz,  // 100 MHz master clock from the FPGA
    input  wire btn_reset,   // Raw push button for reset
    input  wire btn_pause,   // Raw push button for pause
    input  wire sw_adj,      // Slider switch: ADJ (adjust mode)
    input  wire sw_sel,      // Slider switch: SEL (0 = minutes, 1 = seconds)
    output wire [6:0] seg,   // Seven-segment display segments (active low)
    output wire [3:0] an     // Seven-segment display anode controls (active low)
);

  // --------------------------------------------------
  // Debounce the push buttons using the master clock (≈100 MHz)
  // SHOULDE USE MASTER CLOCK HERE INSTEAD
  // --------------------------------------------------
  wire reset_debounced, pause_debounced;
  debounce db_reset(
      .clk(clk_100MHz),
      .btn_in(btn_reset),
      .btn_out(reset_debounced)
  );
  debounce db_pause(
      .clk(clk_100MHz),
      .btn_in(btn_pause),
      .btn_out(pause_debounced)
  );

  // (The slider switches sw_adj and sw_sel are assumed to be stable.)
  wire adjust_debounced, select_debounced;
  debounce db_asjust(
    .clk(clk_100MHz),
    .btn_in(sw_adj),
    .btn_out(adjust_debounced)
  );
  debounce db_select(
    .clk(clk_100MHz),
    .btn_in(sw_sel),
    .btn_out(select_debounced)  // Replace sw_sel with select_debounced below
  );

  // --------------------------------------------------
  // Instantiate the Clock Divider
  // --------------------------------------------------
  wire clk_2Hz, clk_1Hz, clk_fast, clk_blink;
  clock_divider clk_div_inst (
      .clk_100MHz(clk_100MHz),
      .reset(reset_debounced),  // Can also debounce reset if desired
      .clk_2Hz(clk_2Hz),
      .clk_1Hz(clk_1Hz),
      .clk_fast(clk_fast),
      .clk_blink(clk_blink)
  );
  
  // --------------------------------------------------
  // Choose the clock source for the counters based on ADJ and SEL.
  //
  // In normal mode (ADJ low):
  //   - Seconds counter uses clk_1Hz.
  //   - Minutes counter is updated by a pulse (minute_enable) from the seconds counter.
  //
  // In adjust mode (ADJ high):
  //   - If SEL is high, adjust seconds (use clk_2Hz) and freeze minutes.
  //   - If SEL is low, adjust minutes (use clk_2Hz) and freeze seconds.
  // --------------------------------------------------
  wire sec_clk, min_clk, minute_enable;
  
  // For the seconds counter:
  //   - In normal mode: use clk_1Hz.
  //   - In adjust mode for seconds (sw_adj & sw_sel): use clk_2Hz.
  assign sec_clk = (adjust_debounced && select_debounced) ? clk_2Hz : clk_1Hz;
  
  // For the minutes counter:
  //   - In normal mode: update on the seconds counter's minute_enable pulse.
  //   - In adjust mode for minutes (sw_adj & ~sw_sel): use clk_2Hz.
  assign min_clk = (adjust_debounced && ~select_debounced) ? clk_2Hz : minute_enable;
  
  // Generate pause signals:
  // In adjust mode, freeze the unselected counter.
  wire sec_pause, min_pause;
  assign sec_pause = adjust_debounced ? (~select_debounced) : pause_debounced;      // Updated to take in debounced adjust switch
  assign min_pause = adjust_debounced ? ( select_debounced) : pause_debounced;
  
  // --------------------------------------------------
  // Instantiate the Seconds Counter Module
  // --------------------------------------------------
  wire [3:0] sec_ones, sec_tens;
  seconds_counter sec_counter_inst (
      .clk(sec_clk),
      .reset(reset_debounced),
      .pause(sec_pause),
      .sec_ones(sec_ones),
      .sec_tens(sec_tens),
      .minute_enable(minute_enable)  // Pulse to drive minutes counter in normal mode
  );
  
  // --------------------------------------------------
  // Instantiate the Minutes Counter Module
  // --------------------------------------------------
  wire [3:0] min_ones, min_tens;
  minutes_counter min_counter_inst (
      .clk(min_clk),
      .reset(reset_debounced),
      .pause(min_pause),
      .min_ones(min_ones),
      .min_tens(min_tens)
  );
  
  // --------------------------------------------------
  // Combine the 4 digits into a single vector.
  // The ordering is: [min_tens, min_ones, sec_tens, sec_ones]
  // --------------------------------------------------
  wire [15:0] digits;
  assign digits = {min_tens, min_ones, sec_tens, sec_ones};
  
  // --------------------------------------------------
  // Instantiate the Seven-Segment Multiplexer/Driver Module
  // (Make sure the module name here matches the one in sev_segment.v.)
  // --------------------------------------------------
  sev_segment display_inst (
      .clk(clk_fast),
      .clk_blink(clk_blink),
      .adjust(adjust_debounced),  // Adjust mode: if high, blink the selected digits.
      .sel(select_debounced),     // Select: 0 = minutes blink; 1 = seconds blink.
      .digits(digits),
      .seg(seg),
      .an(an)
  );

endmodule

Lab3/stopwatch_tb.v
`timescale 1ns/1ps

module stopwatch_tb;
  // Inputs to the stopwatch
  reg clk_100MHz;
  reg btn_reset;
  reg btn_pause;
  reg sw_adj;
  reg sw_sel;
  
  // Outputs from the stopwatch
  wire [6:0] seg;
  wire [3:0] an;
  
  // Instantiate the stopwatch module
  stopwatch uut (
    .clk_100MHz(clk_100MHz),
    .btn_reset(btn_reset),
    .btn_pause(btn_pause),
    .sw_adj(sw_adj),
    .sw_sel(sw_sel),
    .seg(seg),
    .an(an)
  );

  // ----------------------------------------------------------------
  // 1) Generate 100 MHz clock
  //    Period = 10 ns --> toggle every 5 ns
  // ----------------------------------------------------------------
  initial begin
    clk_100MHz = 0;
    forever #5 clk_100MHz = ~clk_100MHz;
  end
  
  // ----------------------------------------------------------------
  // 2) Dumpfile and dumpvars for GTKWave
  //    After running iverilog, do:  vvp a.out
  //    Then open with:            gtkwave stopwatch_tb.vcd
  // ----------------------------------------------------------------
  initial begin
    $dumpfile("stopwatch_tb.vcd");
    $dumpvars(0, stopwatch_tb);
  end
  
  // ----------------------------------------------------------------
  // 3) Test Stimulus
  //    We do short delays, because real-time seconds would be huge.
  // ----------------------------------------------------------------
  initial begin
    // Initialize inputs
    btn_reset = 0;
    btn_pause = 0;
    sw_adj = 0;
    sw_sel = 0;
    
    // Give some time for the system to come out of reset
    #100;  // 100 ns
    
    // --- Apply a reset pulse ---
    $display("[%t ns] Applying reset...", $time);
    btn_reset = 1;     
    #100;             // hold reset for 100 ns
    btn_reset = 0;
    $display("[%t ns] Released reset.", $time);
    
    // Wait a bit in normal mode
    $display("[%t ns] Let the stopwatch run for a short while in normal mode.", $time);
    #200_000;  // 200 microseconds in simulation; adjust as you like
    
    // --- Pause the stopwatch ---
    $display("[%t ns] Pausing stopwatch...", $time);
    btn_pause = 1;
    #100;
    btn_pause = 0;
    
    // Stay paused for some time
    #50_000; // 50 microseconds
    
    // --- Resume the stopwatch ---
    $display("[%t ns] Resuming stopwatch...", $time);
    btn_pause = 1;
    #100;
    btn_pause = 0;
    
    // Wait a bit again in normal mode
    #150_000;
    
    // --- Enter Adjust Mode (adjust seconds) ---
    $display("[%t ns] Enter adjust mode for seconds...", $time);
    sw_adj = 1;  
    sw_sel = 1;  
    // Let adjustment run for a little while
    #150_000;
    
    // --- Adjust minutes ---
    $display("[%t ns] Switching to adjust minutes...", $time);
    sw_sel = 0;
    #150_000;
    
    // --- Exit adjust mode ---
    $display("[%t ns] Exiting adjust mode...", $time);
    sw_adj = 0;
    
    // Wait a bit in normal mode
    #200_000;
    
    $display("[%t ns] Simulation complete.", $time);
    $stop;
  end

  initial begin
  // In your testbench, after instantiating the stopwatch module:
  $monitor("Time=%t ns | sec_tens=%0d sec_ones=%0d | min_tens=%0d min_ones=%0d",
           $time,
           uut.sec_counter_inst.sec_tens,
           uut.sec_counter_inst.sec_ones,
           uut.min_counter_inst.min_tens,
           uut.min_counter_inst.min_ones
          );
  end

  
endmodule

Lab3/stopwatch_tb.vcd
$date
	Mon Feb 24 17:37:11 2025
$end
$version
	Icarus Verilog
$end
$timescale
	1ps
$end
$scope module stopwatch_tb $end
$var wire 7 ! seg [6:0] $end
$var wire 4 " an [3:0] $end
$var reg 1 # btn_pause $end
$var reg 1 $ btn_reset $end
$var reg 1 % clk_100MHz $end
$var reg 1 & sw_adj $end
$var reg 1 ' sw_sel $end
$scope module uut $end
$var wire 1 # btn_pause $end
$var wire 1 $ btn_reset $end
$var wire 1 % clk_100MHz $end
$var wire 1 & sw_adj $end
$var wire 1 ' sw_sel $end
$var wire 1 ( select_debounced $end
$var wire 7 ) seg [6:0] $end
$var wire 4 * sec_tens [3:0] $end
$var wire 1 + sec_pause $end
$var wire 4 , sec_ones [3:0] $end
$var wire 1 - sec_clk $end
$var wire 1 . reset_debounced $end
$var wire 1 / pause_debounced $end
$var wire 1 0 minute_enable $end
$var wire 4 1 min_tens [3:0] $end
$var wire 1 2 min_pause $end
$var wire 4 3 min_ones [3:0] $end
$var wire 1 4 min_clk $end
$var wire 16 5 digits [15:0] $end
$var wire 1 6 clk_fast $end
$var wire 1 7 clk_blink $end
$var wire 1 8 clk_2Hz $end
$var wire 1 9 clk_1Hz $end
$var wire 4 : an [3:0] $end
$var wire 1 ; adjust_debounced $end
$scope module clk_div_inst $end
$var wire 1 % clk_100MHz $end
$var wire 1 . reset $end
$var parameter 32 < DIV_1HZ $end
$var parameter 32 = DIV_2HZ $end
$var parameter 32 > DIV_BLINK $end
$var parameter 32 ? DIV_FAST $end
$var reg 1 9 clk_1Hz $end
$var reg 1 8 clk_2Hz $end
$var reg 1 7 clk_blink $end
$var reg 1 6 clk_fast $end
$var reg 26 @ counter_1Hz [25:0] $end
$var reg 26 A counter_2Hz [25:0] $end
$var reg 26 B counter_blink [25:0] $end
$var reg 26 C counter_fast [25:0] $end
$upscope $end
$scope module db_asjust $end
$var wire 1 & btn_in $end
$var wire 1 % clk $end
$var reg 1 ; btn_out $end
$var reg 16 D shift_reg [15:0] $end
$upscope $end
$scope module db_pause $end
$var wire 1 # btn_in $end
$var wire 1 % clk $end
$var reg 1 / btn_out $end
$var reg 16 E shift_reg [15:0] $end
$upscope $end
$scope module db_reset $end
$var wire 1 $ btn_in $end
$var wire 1 % clk $end
$var reg 1 . btn_out $end
$var reg 16 F shift_reg [15:0] $end
$upscope $end
$scope module db_select $end
$var wire 1 ' btn_in $end
$var wire 1 % clk $end
$var reg 1 ( btn_out $end
$var reg 16 G shift_reg [15:0] $end
$upscope $end
$scope module display_inst $end
$var wire 1 ; adjust $end
$var wire 1 6 clk $end
$var wire 1 7 clk_blink $end
$var wire 16 H digits [15:0] $end
$var wire 1 ( sel $end
$var reg 4 I an [3:0] $end
$var reg 1 J blink $end
$var reg 4 K digit [3:0] $end
$var reg 2 L digit_sel [1:0] $end
$var reg 7 M seg [6:0] $end
$var reg 7 N seg_temp [6:0] $end
$upscope $end
$scope module min_counter_inst $end
$var wire 1 4 clk $end
$var wire 1 O en $end
$var wire 1 2 pause $end
$var wire 1 . reset $end
$var wire 1 P ones_carry $end
$var wire 4 Q min_tens [3:0] $end
$var wire 4 R min_ones [3:0] $end
$scope module ones_counter $end
$var wire 1 4 clk $end
$var wire 1 O en $end
$var wire 1 . reset $end
$var reg 1 P carry $end
$var reg 4 S count [3:0] $end
$upscope $end
$scope module tens_counter $end
$var wire 1 4 clk $end
$var wire 1 P en $end
$var wire 1 . reset $end
$var reg 1 T carry $end
$var reg 4 U count [3:0] $end
$upscope $end
$upscope $end
$scope module sec_counter_inst $end
$var wire 1 - clk $end
$var wire 1 V en $end
$var wire 1 + pause $end
$var wire 1 . reset $end
$var wire 4 W sec_tens [3:0] $end
$var wire 4 X sec_ones [3:0] $end
$var wire 1 Y ones_carry $end
$var wire 1 0 minute_enable $end
$scope module ones_counter $end
$var wire 1 - clk $end
$var wire 1 V en $end
$var wire 1 . reset $end
$var reg 1 Y carry $end
$var reg 4 Z count [3:0] $end
$upscope $end
$scope module tens_counter $end
$var wire 1 - clk $end
$var wire 1 Y en $end
$var wire 1 . reset $end
$var reg 1 0 carry $end
$var reg 4 [ count [3:0] $end
$upscope $end
$upscope $end
$upscope $end
$upscope $end
$enddefinitions $end
$comment Show the parameter values. $end
$dumpall
b111101000010010000 ?
b1110111001101011001010000 >
b1011111010111100001000000 =
b10111110101111000010000000 <
$end
#0
$dumpvars
bx [
bx Z
xY
bx X
bx W
xV
bx U
xT
bx S
bx R
bx Q
xP
xO
bx N
bx M
b0 L
bx K
1J
b111 I
bx H
b0 G
b0 F
b0 E
b0 D
bx C
bx B
bx A
bx @
x;
b111 :
x9
x8
x7
x6
bx 5
x4
bx 3
x2
bx 1
x0
x/
x.
x-
bx ,
x+
bx *
bx )
x(
0'
0&
0%
0$
0#
b111 "
bx !
$end
#5000
1V
1O
0+
02
0.
0/
0;
0(
1%
#10000
0%
#15000
1%
#20000
0%
#25000
1%
#30000
0%
#35000
1%
#40000
0%
#45000
1%
#50000
0%
#55000
1%
#60000
0%
#65000
1%
#70000
0%
#75000
1%
#80000
0%
#85000
1%
#90000
0%
#95000
1%
#100000
0%
1$
#105000
b1 F
1%
#110000
0%
#115000
b11 F
1%
#120000
0%
#125000
b111 F
1%
#130000
0%
#135000
b1111 F
1%
#140000
0%
#145000
b11111 F
1%
#150000
0%
#155000
b111111 F
1%
#160000
0%
#165000
b1111111 F
1%
#170000
0%
#175000
b11111111 F
1%
#180000
0%
#185000
b111111111 F
1%
#190000
0%
#195000
b1111111111 F
1%
#200000
0%
0$
#205000
b11111111110 F
1%
#210000
0%
#215000
b111111111100 F
1%
#220000
0%
#225000
b1111111111000 F
1%
#230000
0%
#235000
b11111111110000 F
1%
#240000
0%
#245000
b111111111100000 F
1%
#250000
0%
#255000
b1111111111000000 F
1%
#260000
0%
#265000
b1111111110000000 F
1%
#270000
0%
#275000
b1111111100000000 F
1%
#280000
0%
#285000
b1111111000000000 F
1%
#290000
0%
#295000
b1111110000000000 F
1%
#300000
0%
#305000
b1111100000000000 F
1%
#310000
0%
#315000
b1111000000000000 F
1%
#320000
0%
#325000
b1110000000000000 F
1%
#330000
0%
#335000
b1100000000000000 F
1%
#340000
0%
#345000
b1000000000000000 F
1%
#350000
0%
#355000
b0 F
1%
